isympy.py
displaylang_sympy-0.10.4.data/data/share/man/man1/isympy.1
sympy/__init__.py
sympy/abc.py
sympy/conftest.py
sympy/galgebra.py
sympy/py.typed
sympy/release.py
sympy/this.py
sympy/algebras/__init__.py
sympy/algebras/quaternion.py
sympy/algebras/tests/__init__.py
sympy/algebras/tests/test_quaternion.py
sympy/assumptions/__init__.py
sympy/assumptions/ask.py
sympy/assumptions/ask_generated.py
sympy/assumptions/assume.py
sympy/assumptions/cnf.py
sympy/assumptions/facts.py
sympy/assumptions/refine.py
sympy/assumptions/satask.py
sympy/assumptions/sathandlers.py
sympy/assumptions/wrapper.py
sympy/assumptions/handlers/__init__.py
sympy/assumptions/handlers/calculus.py
sympy/assumptions/handlers/common.py
sympy/assumptions/handlers/matrices.py
sympy/assumptions/handlers/ntheory.py
sympy/assumptions/handlers/order.py
sympy/assumptions/handlers/sets.py
sympy/assumptions/predicates/__init__.py
sympy/assumptions/predicates/calculus.py
sympy/assumptions/predicates/common.py
sympy/assumptions/predicates/matrices.py
sympy/assumptions/predicates/ntheory.py
sympy/assumptions/predicates/order.py
sympy/assumptions/predicates/sets.py
sympy/assumptions/relation/__init__.py
sympy/assumptions/relation/binrel.py
sympy/assumptions/relation/equality.py
sympy/assumptions/tests/__init__.py
sympy/assumptions/tests/test_assumptions_2.py
sympy/assumptions/tests/test_context.py
sympy/assumptions/tests/test_matrices.py
sympy/assumptions/tests/test_query.py
sympy/assumptions/tests/test_refine.py
sympy/assumptions/tests/test_satask.py
sympy/assumptions/tests/test_sathandlers.py
sympy/assumptions/tests/test_wrapper.py
sympy/benchmarks/__init__.py
sympy/benchmarks/bench_discrete_log.py
sympy/benchmarks/bench_meijerint.py
sympy/benchmarks/bench_symbench.py
sympy/calculus/__init__.py
sympy/calculus/accumulationbounds.py
sympy/calculus/euler.py
sympy/calculus/finite_diff.py
sympy/calculus/singularities.py
sympy/calculus/util.py
sympy/calculus/tests/__init__.py
displaylang_sympy-0.10.4.dist-info/AUTHORS
displaylang_sympy-0.10.4.dist-info/LICENSE
displaylang_sympy-0.10.4.dist-info/METADATA
displaylang_sympy-0.10.4.dist-info/WHEEL
displaylang_sympy-0.10.4.dist-info/entry_points.txt
displaylang_sympy-0.10.4.dist-info/top_level.txt
displaylang_sympy-0.10.4.dist-info/RECORD
