Metadata-Version: 2.1
Name: displaylang-sympy
Version: 0.10.4
Summary: The DisplayLang fork of SymPy
Home-page: UNKNOWN
Author: SymPy development team + DisplayLang contributors
License: BSD
Project-URL: Source, https://github.com/proofscape/sympy
Keywords: Math CAS
Platform: UNKNOWN
Classifier: License :: OSI Approved :: BSD License
Classifier: Operating System :: OS Independent
Classifier: Programming Language :: Python
Classifier: Topic :: Scientific/Engineering
Classifier: Topic :: Scientific/Engineering :: Mathematics
Classifier: Topic :: Scientific/Engineering :: Physics
Classifier: Programming Language :: Python :: 3
Classifier: Programming Language :: Python :: 3.8
Classifier: Programming Language :: Python :: 3.9
Classifier: Programming Language :: Python :: 3.10
Classifier: Programming Language :: Python :: 3 :: Only
Classifier: Programming Language :: Python :: Implementation :: CPython
Classifier: Programming Language :: Python :: Implementation :: PyPy
Requires-Python: >=3.8
Requires-Dist: displaylang (>=0.22.8)
Requires-Dist: mpmath (>=0.19)
